accounts/__init__.py
accounts/admin.py
accounts/apps.py
accounts/forms.py
accounts/models.py
accounts/tests.py
accounts/token.py
accounts/urls.py
accounts/views.py
accounts/migrations/0001_initial.py
accounts/migrations/__init__.py
cloud/__init__.py
cloud/admin.py
cloud/apps.py
cloud/cart.py
cloud/models.py
cloud/tests.py
cloud/views.py
cloud/migrations/0001_initial.py
cloud/migrations/__init__.py
geolocation/__init__.py
geolocation/admin.py
geolocation/apps.py
geolocation/models.py
geolocation/tests.py
geolocation/views.py
geolocation/migrations/0001_initial.py
geolocation/migrations/__init__.py
home/migrations/__init__.py
stela_control/__init__.py
stela_control/admin.py
stela_control/apps.py
stela_control/cart.py
stela_control/context_processors.py
stela_control/cron.py
stela_control/forms.py
stela_control/functions.py
stela_control/models.py
stela_control/routers.py
stela_control/superfunctions.py
stela_control/tasks.py
stela_control/tests.py
stela_control/tokenize.py
stela_control/urls.py
stela_control/views.py
stela_control/locale/es/LC_MESSAGES/django.mo
stela_control/locale/es/LC_MESSAGES/django.po
stela_control/migrations/0001_initial.py
stela_control/migrations/0002_alter_billingrecipt_option_alter_company_business_and_more.py
stela_control/migrations/0003_rename_description_company_content_and_more.py
stela_control/migrations/0004_alter_billingrecipt_option_alter_company_address_and_more.py
stela_control/migrations/0005_rename_description_team_content_and_more.py
stela_control/migrations/0006_alter_bankstatement_bank_and_more.py
stela_control/migrations/0007_alter_billingrecipt_option_alter_company_business_and_more.py
stela_control/migrations/0008_alter_billingrecipt_option_alter_company_business_and_more.py
stela_control/migrations/0009_content_video_alter_billingrecipt_option_and_more.py
stela_control/migrations/0010_resource_category_alter_billingrecipt_option_and_more.py
stela_control/migrations/0011_resource_cover_taxid_pdf_file2_and_more.py
steladjango_professional-0.1.6.dist-info/METADATA
steladjango_professional-0.1.6.dist-info/WHEEL
steladjango_professional-0.1.6.dist-info/top_level.txt
steladjango_professional-0.1.6.dist-info/RECORD
